<?xml version="1.0" standalone="yes"?>
<?xml-stylesheet type='text/xsl' href='TheWord.xslt'?>
<wordOfGod>
 <TheWord>

  <SequenceOrderId>226</SequenceOrderId>
  <Dated>2003-10-25T00:00:00.0000000-08:00</Dated>
  <ScriptureReference>Matthew 17:12, Mark 9:13</ScriptureReference>
  <ScriptureReferenceURI>http://bible.crosswalk.com/OnlineStudyBible/bible.cgi?new=1&amp;word=Matthew+17%3A12%2C+Mark+9%3A13&amp;section=0&amp;version=nkj&amp;language=en</ScriptureReferenceURI>
  <Title>You have to come to a better realization of Him.</Title>
  <Commentary>As our house grow let it grow with You. (Right eye tears ... green grass towards the left.)</Commentary>

  <!--
  <JehovahRophe>
   <SequenceOrderId>32</SequenceOrderId>
   <Commentary></Commentary>
  </JehovahRophe>
  -->

  <!--
  <Dream>
   <SequenceOrderId>6</SequenceOrderId>
   <Commentary></Commentary>
  </Dream>
  -->

  <!--
  <Prophet>
   <SequenceOrderId>104</SequenceOrderId>
   <Commentary>
   </Commentary>
  </Prophet>
  -->

  <!--
  <Remember>
   <SequenceOrderId>459</SequenceOrderId>
   <DatedFrom></DatedFrom>
   <DatedUntil></DatedUntil>
   <FromUntil></FromUntil>
   <Commentary></Commentary>
   <ScriptureReference></ScriptureReference>
   <ScriptureReferenceURI></ScriptureReferenceURI>
   <Filename></Filename>
  </Remember>
  -->

  <!--
  <ScriptureReading>
   <SequenceOrderId>80</SequenceOrderId>
   <ScriptureReference></ScriptureReference>
   <ScriptureReferenceURI></ScriptureReferenceURI>
  </ScriptureReading>
  -->

  <!--
  <Sign>
   <SequenceOrderId>36</SequenceOrderId>
   <Measure></Measure>
   <SignIndex></SignIndex>
   <Commentary></Commentary>
   <ScriptureReference></ScriptureReference>
   <ScriptureReferenceURI></ScriptureReferenceURI>
  </Sign>
  -->

  <BibleWord>
   <SequenceOrderId>408</SequenceOrderId>
   <Word>You ... Elias ... Him</Word>
  </BibleWord>

  <AlphabetSequence>
   <SequenceOrderId>858</SequenceOrderId>
   <Word>You have to come to a better realization of Him.</Word>
   <AlphabetSequenceIndex>455</AlphabetSequenceIndex>
   <ScriptureReference>Genesis 18:30, Job 19, Isaiah 56, 2 John 1:2</ScriptureReference>
   <ScriptureReferenceURI>http://bible.crosswalk.com/OnlineStudyBible/bible.cgi?new=1&amp;word=Genesis+18%3A30%2C+Job+19%2C+Isaiah+56%2C+2+John+1%3A2&amp;section=0&amp;version=nkj&amp;language=en</ScriptureReferenceURI>
  </AlphabetSequence>

  <CaseBasedReasoning>
   <SequenceOrderId>1271</SequenceOrderId>
   <Commentary>Kokuho Rice U.S. #1 Extra Fancy New Crop Net Wt. 20LBS 9.07kg: Half filling. Kokuho Rice U.S. #1 Extra Fancy New Crop Net Wt. 20LBS 9.07kg: Cooking. Half cooked rice seed on the center of 5 buttons.</Commentary>
  </CaseBasedReasoning>

  <!--
  <Export>
   <SequenceOrderId>26</SequenceOrderId>
   <Commentary></Commentary>
  </Export>
  -->

  <!--
  <Software>
   <SequenceOrderId>281</SequenceOrderId>
   <Commentary></Commentary>
  </Software>
  -->

  <ClassAssociates>
   <SequenceOrderId>480</SequenceOrderId>
   <Commentary>Shutdown the left computer, Comfort ... Comfort computer noise.</Commentary>
  </ClassAssociates>

 </TheWord>
</wordOfGod>