<?xml version="1.0" standalone="yes"?>
<?xml-stylesheet type='text/xsl' href='TheWord.xslt'?>
<wordOfGod>
  <TheWord>
    <Dated>2004-10-22T00:00:00.0000000-07:00</Dated>
    <Title>Continue to afford this people a chance to give your opportunity to all people.
A mediocre rarely realitate his taste.
You have to decide how you find percentage of measurement in an absent world.
You take what you don't own; you lose what you don't own have.
Rarely do we appease our gods in our father's ancestry.
Harshly we treated the minority, mainly in an unsocial climate.
Its our example to accelerate changes when we face forgotten in the future.
For each of us, God has different mannerism of selling the seller.
Unfortunately creativity is lost when spys smear undeveloped tongue.
In the middle of the lane, you don't deserve a zone.
We continue to hold on to a land that does not forsake its savior.
</Title>
  </TheWord>
  <AlphabetSequence>
    <SequenceOrderId>10554</SequenceOrderId>
    <Word>Continue to afford this people a chance to give your opportunity to all people.</Word>
    <AlphabetSequenceIndex>821</AlphabetSequenceIndex>
    <ScriptureReference>Genesis 29:25, Ezekiel 19, 1 Chronicles 26, James 1:15</ScriptureReference>
    <ScriptureReferenceURI>http://bible.crosswalk.com/OnlineStudyBible/bible.cgi?new=1&amp;word=Genesis+29%3A25%2C+Ezekiel+19%2C+1+Chronicles+26%2C+James+1%3A15&amp;section=0&amp;version=nkj&amp;language=en</ScriptureReferenceURI>
  </AlphabetSequence>
  <AlphabetSequence>
    <SequenceOrderId>10555</SequenceOrderId>
    <Word>A mediocre rarely realitate his taste.</Word>
    <AlphabetSequenceIndex>344</AlphabetSequenceIndex>
    <ScriptureReference>Genesis 14:7, 1 Chronicles 6, Ezekiel 39, Revelation 3:12</ScriptureReference>
    <ScriptureReferenceURI>http://bible.crosswalk.com/OnlineStudyBible/bible.cgi?new=1&amp;word=Genesis+14%3A7%2C+1+Chronicles+6%2C+Ezekiel+39%2C+Revelation+3%3A12&amp;section=0&amp;version=nkj&amp;language=en</ScriptureReferenceURI>
  </AlphabetSequence>
  <AlphabetSequence>
    <SequenceOrderId>10556</SequenceOrderId>
    <Word>You have to decide how you find percentage of measurement in an absent world.</Word>
    <AlphabetSequenceIndex>722</AlphabetSequenceIndex>
    <ScriptureReference>Genesis 26:29, Isaiah 43, Job 27, 1 Peter 1:6</ScriptureReference>
    <ScriptureReferenceURI>http://bible.crosswalk.com/OnlineStudyBible/bible.cgi?new=1&amp;word=Genesis+26%3A29%2C+Isaiah+43%2C+Job+27%2C+1+Peter+1%3A6&amp;section=0&amp;version=nkj&amp;language=en</ScriptureReferenceURI>
  </AlphabetSequence>
  <AlphabetSequence>
    <SequenceOrderId>10557</SequenceOrderId>
    <Word>You take what you don't own; you lose what you don't own have.</Word>
    <AlphabetSequenceIndex>682</AlphabetSequenceIndex>
    <ScriptureReference>Genesis 25:23, Isaiah 3, Psalms 25, 1 Peter 2:21</ScriptureReference>
    <ScriptureReferenceURI>http://bible.crosswalk.com/OnlineStudyBible/bible.cgi?new=1&amp;word=Genesis+25%3A23%2C+Isaiah+3%2C+Psalms+25%2C+1+Peter+2%3A21&amp;section=0&amp;version=nkj&amp;language=en</ScriptureReferenceURI>
  </AlphabetSequence>
  <AlphabetSequence>
    <SequenceOrderId>10558</SequenceOrderId>
    <Word>Rarely do we appease our gods in our father's ancestry.</Word>
    <AlphabetSequenceIndex>547</AlphabetSequenceIndex>
    <ScriptureReference>Genesis 21:33, Psalms 69, Proverbs 10, 1 John 2:5</ScriptureReference>
    <ScriptureReferenceURI>http://bible.crosswalk.com/OnlineStudyBible/bible.cgi?new=1&amp;word=Genesis+21%3A33%2C+Psalms+69%2C+Proverbs+10%2C+1+John+2%3A5&amp;section=0&amp;version=nkj&amp;language=en</ScriptureReferenceURI>
  </AlphabetSequence>
  <AlphabetSequence>
    <SequenceOrderId>10559</SequenceOrderId>
    <Word>Harshly we treated the minority, mainly in an unsocial climate.</Word>
    <AlphabetSequenceIndex>617</AlphabetSequenceIndex>
    <ScriptureReference>Genesis 24:25, Psalms 139, Psalms 90, 2 Peter 1:6</ScriptureReference>
    <ScriptureReferenceURI>http://bible.crosswalk.com/OnlineStudyBible/bible.cgi?new=1&amp;word=Genesis+24%3A25%2C+Psalms+139%2C+Psalms+90%2C+2+Peter+1%3A6&amp;section=0&amp;version=nkj&amp;language=en</ScriptureReferenceURI>
  </AlphabetSequence>
  <AlphabetSequence>
    <SequenceOrderId>10560</SequenceOrderId>
    <Word>Its our example to accelerate changes when we face forgotten in the future.</Word>
    <AlphabetSequenceIndex>703</AlphabetSequenceIndex>
    <ScriptureReference>Genesis 26:10, Isaiah 24, Psalms 4, 1 Peter 1:25</ScriptureReference>
    <ScriptureReferenceURI>http://bible.crosswalk.com/OnlineStudyBible/bible.cgi?new=1&amp;word=Genesis+26%3A10%2C+Isaiah+24%2C+Psalms+4%2C+1+Peter+1%3A25&amp;section=0&amp;version=nkj&amp;language=en</ScriptureReferenceURI>
  </AlphabetSequence>
  <AlphabetSequence>
    <SequenceOrderId>10561</SequenceOrderId>
    <Word>For each of us, God has different mannerism of selling the seller.</Word>
    <AlphabetSequenceIndex>567</AlphabetSequenceIndex>
    <ScriptureReference>Genesis 22:19, Psalms 89, Psalms 140, 2 Peter 3:13</ScriptureReference>
    <ScriptureReferenceURI>http://bible.crosswalk.com/OnlineStudyBible/bible.cgi?new=1&amp;word=Genesis+22%3A19%2C+Psalms+89%2C+Psalms+140%2C+2+Peter+3%3A13&amp;section=0&amp;version=nkj&amp;language=en</ScriptureReferenceURI>
  </AlphabetSequence>
  <AlphabetSequence>
    <SequenceOrderId>10562</SequenceOrderId>
    <Word>Unfortunately creativity is lost when spys smear undeveloped tongue.</Word>
    <AlphabetSequenceIndex>808</AlphabetSequenceIndex>
    <ScriptureReference>Genesis 29:12, Ezekiel 6, 2 Chronicles 10, James 2:1</ScriptureReference>
    <ScriptureReferenceURI>http://bible.crosswalk.com/OnlineStudyBible/bible.cgi?new=1&amp;word=Genesis+29%3A12%2C+Ezekiel+6%2C+2+Chronicles+10%2C+James+2%3A1&amp;section=0&amp;version=nkj&amp;language=en</ScriptureReferenceURI>
  </AlphabetSequence>
  <AlphabetSequence>
    <SequenceOrderId>10563</SequenceOrderId>
    <Word>In the middle of the lane, you don't deserve a zone.</Word>
    <AlphabetSequenceIndex>442</AlphabetSequenceIndex>
    <ScriptureReference>Genesis 18:17, Job 6, Isaiah 64, 3 John 1:2</ScriptureReference>
    <ScriptureReferenceURI>http://bible.crosswalk.com/OnlineStudyBible/bible.cgi?new=1&amp;word=Genesis+18%3A17%2C+Job+6%2C+Isaiah+64%2C+3+John+1%3A2&amp;section=0&amp;version=nkj&amp;language=en</ScriptureReferenceURI>
  </AlphabetSequence>
  <AlphabetSequence>
    <SequenceOrderId>10564</SequenceOrderId>
    <Word>We continue to hold on to a land that does not forsake its savior.</Word>
    <AlphabetSequenceIndex>647</AlphabetSequenceIndex>
    <ScriptureReference>Genesis 24:55, Proverbs 19, Psalms 60, 1 Peter 4:9</ScriptureReference>
    <ScriptureReferenceURI>http://bible.crosswalk.com/OnlineStudyBible/bible.cgi?new=1&amp;word=Genesis+24%3A55%2C+Proverbs+19%2C+Psalms+60%2C+1+Peter+4%3A9&amp;section=0&amp;version=nkj&amp;language=en</ScriptureReferenceURI>
  </AlphabetSequence>
</wordOfGod>