<?xml version="1.0" standalone="yes"?>
<?xml-stylesheet type='text/xsl' href='TheWord.xslt'?>
<TheWord>
 <SequenceOrderId>723</SequenceOrderId>
 <Dated>2004-12-11T10:35:00.0000000-08:00</Dated>
 <FromUntil>346</FromUntil>
 <ContactId>1193</ContactId>
 <Keyword>Activism, offer acception, distance associating, fore fathers beings, lack the climate, play together, share together, characterization control, american product living</Keyword>
 <ScriptureReference>1 Samuel 25:17</ScriptureReference>
 <ScriptureReferenceURI>http://bible.crosswalk.com/OnlineStudyBible/bible.cgi?new=1&amp;word=1+Samuel+25%3A17&amp;section=0&amp;version=nkj&amp;language=en</ScriptureReferenceURI>
 <Commentary>Its american product living in outside life.</Commentary>
 
  <!--
  <Anointing>
   <SequenceOrderId>4</SequenceOrderId>
   <Rhema></Rhema>
   <Commentary></Commentary>
   <Filename />
  </Anointing>
  -->

  <!--
  <JehovahRophe>
   <SequenceOrderId>59</SequenceOrderId>
   <Commentary></Commentary>
  </JehovahRophe>
  -->

  <!--
  <Dream>
   <SequenceOrderId>146</SequenceOrderId>
   <Commentary></Commentary>
  </Dream>
  -->

  <!--
  <Prophet>
   <SequenceOrderId>114</SequenceOrderId>
   <Commentary></Commentary>
  </Prophet>
  -->

  <!--
  <Remember>
   <SequenceOrderId>690</SequenceOrderId>
   <DatedFrom></DatedFrom>
   <DatedUntil></DatedUntil>
   <FromUntil></FromUntil>
   <Filename></Filename>
   <Commentary></Commentary>
   <ScriptureReference></ScriptureReference>
   <ScriptureReferenceURI></ScriptureReferenceURI>
  </Remember>
  -->
  
  <!--
  <ScriptureReading>
   <SequenceOrderId>91</SequenceOrderId>
   <ScriptureReference></ScriptureReference>
   <ScriptureReferenceURI></ScriptureReferenceURI>
  </ScriptureReading>
  -->

  <!--
  <Sign>
   <SequenceOrderId>36</SequenceOrderId>
   <Measure></Measure>
   <SignIndex></SignIndex>
   <Commentary></Commentary>
   <ScriptureReference></ScriptureReference>
   <ScriptureReferenceURI></ScriptureReferenceURI>
  </Sign>
  -->

  <BibleWord>
   <SequenceOrderId>656</SequenceOrderId>
   <Word>House Hold Him not can</Word>
   <ScriptureReference>1 Samuel 25:17</ScriptureReference>
   <ScriptureReferenceURI>http://bible.crosswalk.com/OnlineStudyBible/bible.cgi?new=1&amp;word=1+Samuel+25%3A17&amp;section=0&amp;version=nkj&amp;language=en</ScriptureReferenceURI>
  </BibleWord>

  <!--
  <NameIdentity>
   <SequenceOrderId>27</SequenceOrderId>
   <IssuedAlliance></IssuedAlliance>
   <InclusiveLiteral />
   <Commentary></Commentary>
   <ContactId></ContactId>
   <Dated></Dated>
  </NameIdentity>
  -->

  <!--
  <KaiserPermanenteBloodPressure>
   <Dated></Dated>
   <SequenceOrderId>2</SequenceOrderId>
   <Systolic></Systolic>
   <Diastolic></Diastolic>
   <Pulse></Pulse>
   <ContactId></ContactId>
  </KaiserPermanenteBloodPressure>
  -->

  <AlphabetSequence>
    <SequenceOrderId>12669</SequenceOrderId>
    <Word>I will not house him, if I can't hold him.</Word>
    <AlphabetSequenceIndex>343</AlphabetSequenceIndex>
    <ScriptureReference>Genesis 14:6, 1 Chronicles 5, Ezekiel 40, Revelation 3:13</ScriptureReference>
    <ScriptureReferenceURI>http://bible.crosswalk.com/OnlineStudyBible/bible.cgi?new=1&amp;word=Genesis+14%3A6%2C+1+Chronicles+5%2C+Ezekiel+40%2C+Revelation+3%3A13&amp;section=0&amp;version=nkj&amp;language=en</ScriptureReferenceURI>
  </AlphabetSequence>
  <AlphabetSequence>
    <SequenceOrderId>12670</SequenceOrderId>
    <Word>He skipped college to act activism.</Word>
    <AlphabetSequenceIndex>307</AlphabetSequenceIndex>
    <ScriptureReference>Genesis 12:8, 1 Kings 16, Joel 2, Revelation 6:2</ScriptureReference>
    <ScriptureReferenceURI>http://bible.crosswalk.com/OnlineStudyBible/bible.cgi?new=1&amp;word=Genesis+12%3A8%2C+1+Kings+16%2C+Joel+2%2C+Revelation+6%3A2&amp;section=0&amp;version=nkj&amp;language=en</ScriptureReferenceURI>
  </AlphabetSequence>
  <AlphabetSequence>
    <SequenceOrderId>12671</SequenceOrderId>
    <Word>You won't dispute his class.</Word>
    <AlphabetSequenceIndex>317</AlphabetSequenceIndex>
    <ScriptureReference>Genesis 12:18, 2 Kings 4, Hosea 6, Revelation 5:6</ScriptureReference>
    <ScriptureReferenceURI>http://bible.crosswalk.com/OnlineStudyBible/bible.cgi?new=1&amp;word=Genesis+12%3A18%2C+2+Kings+4%2C+Hosea+6%2C+Revelation+5%3A6&amp;section=0&amp;version=nkj&amp;language=en</ScriptureReferenceURI>
  </AlphabetSequence>
  <AlphabetSequence>
    <SequenceOrderId>12672</SequenceOrderId>
    <Word>As for my distribution, I summarize the cost.</Word>
    <AlphabetSequenceIndex>481</AlphabetSequenceIndex>
    <ScriptureReference>Genesis 19:23, Psalms 3, Isaiah 25, 1 John 4:18</ScriptureReference>
    <ScriptureReferenceURI>http://bible.crosswalk.com/OnlineStudyBible/bible.cgi?new=1&amp;word=Genesis+19%3A23%2C+Psalms+3%2C+Isaiah+25%2C+1+John+4%3A18&amp;section=0&amp;version=nkj&amp;language=en</ScriptureReferenceURI>
  </AlphabetSequence>
  <AlphabetSequence>
    <SequenceOrderId>12673</SequenceOrderId>
    <Word>You saw the way she wants to be presented among her living relative.</Word>
    <AlphabetSequenceIndex>689</AlphabetSequenceIndex>
    <ScriptureReference>Genesis 25:30, Isaiah 10, Psalms 18, 1 Peter 2:14</ScriptureReference>
    <ScriptureReferenceURI>http://bible.crosswalk.com/OnlineStudyBible/bible.cgi?new=1&amp;word=Genesis+25%3A30%2C+Isaiah+10%2C+Psalms+18%2C+1+Peter+2%3A14&amp;section=0&amp;version=nkj&amp;language=en</ScriptureReferenceURI>
  </AlphabetSequence>
  <AlphabetSequence>
    <SequenceOrderId>12674</SequenceOrderId>
    <Word>The president only appoints sociable men.</Word>
    <AlphabetSequenceIndex>417</AlphabetSequenceIndex>
    <ScriptureReference>Genesis 17:19, Nehemiah 4, Jeremiah 23, Jude 1:13</ScriptureReference>
    <ScriptureReferenceURI>http://bible.crosswalk.com/OnlineStudyBible/bible.cgi?new=1&amp;word=Genesis+17%3A19%2C+Nehemiah+4%2C+Jeremiah+23%2C+Jude+1%3A13&amp;section=0&amp;version=nkj&amp;language=en</ScriptureReferenceURI>
  </AlphabetSequence>
  <AlphabetSequence>
    <SequenceOrderId>12675</SequenceOrderId>
    <Word>You have to find your less given.</Word>
    <AlphabetSequenceIndex>356</AlphabetSequenceIndex>
    <ScriptureReference>Genesis 14:19, 1 Chronicles 18, Ezekiel 27, Revelation 2:29</ScriptureReference>
    <ScriptureReferenceURI>http://bible.crosswalk.com/OnlineStudyBible/bible.cgi?new=1&amp;word=Genesis+14%3A19%2C+1+Chronicles+18%2C+Ezekiel+27%2C+Revelation+2%3A29&amp;section=0&amp;version=nkj&amp;language=en</ScriptureReferenceURI>
  </AlphabetSequence>
  <AlphabetSequence>
    <SequenceOrderId>12676</SequenceOrderId>
    <Word>He won't rather lose you abroad.</Word>
    <AlphabetSequenceIndex>308</AlphabetSequenceIndex>
    <ScriptureReference>Genesis 12:9, 1 Kings 17, Joel 1, Revelation 6:1</ScriptureReference>
    <ScriptureReferenceURI>http://bible.crosswalk.com/OnlineStudyBible/bible.cgi?new=1&amp;word=Genesis+12%3A9%2C+1+Kings+17%2C+Joel+1%2C+Revelation+6%3A1&amp;section=0&amp;version=nkj&amp;language=en</ScriptureReferenceURI>
  </AlphabetSequence>
  <AlphabetSequence>
    <SequenceOrderId>12677</SequenceOrderId>
    <Word>We have presentable gentlemen waiting outside.</Word>
    <AlphabetSequenceIndex>452</AlphabetSequenceIndex>
    <ScriptureReference>Genesis 18:27, Job 16, Isaiah 54, 2 John 1:5</ScriptureReference>
    <ScriptureReferenceURI>http://bible.crosswalk.com/OnlineStudyBible/bible.cgi?new=1&amp;word=Genesis+18%3A27%2C+Job+16%2C+Isaiah+54%2C+2+John+1%3A5&amp;section=0&amp;version=nkj&amp;language=en</ScriptureReferenceURI>
  </AlphabetSequence>
  <AlphabetSequence>
    <SequenceOrderId>12678</SequenceOrderId>
    <Word>Once again in history is everybody's time.</Word>
    <AlphabetSequenceIndex>421</AlphabetSequenceIndex>
    <ScriptureReference>Genesis 17:23, Nehemiah 8, Jeremiah 19, Jude 1:9</ScriptureReference>
    <ScriptureReferenceURI>http://bible.crosswalk.com/OnlineStudyBible/bible.cgi?new=1&amp;word=Genesis+17%3A23%2C+Nehemiah+8%2C+Jeremiah+19%2C+Jude+1%3A9&amp;section=0&amp;version=nkj&amp;language=en</ScriptureReferenceURI>
  </AlphabetSequence>
  <AlphabetSequence>
    <SequenceOrderId>12679</SequenceOrderId>
    <Word>Each day is allocatable to our resources.</Word>
    <AlphabetSequenceIndex>371</AlphabetSequenceIndex>
    <ScriptureReference>Genesis 15:10, 2 Chronicles 4, Ezekiel 12, Revelation 2:14</ScriptureReference>
    <ScriptureReferenceURI>http://bible.crosswalk.com/OnlineStudyBible/bible.cgi?new=1&amp;word=Genesis+15%3A10%2C+2+Chronicles+4%2C+Ezekiel+12%2C+Revelation+2%3A14&amp;section=0&amp;version=nkj&amp;language=en</ScriptureReferenceURI>
  </AlphabetSequence>
  <AlphabetSequence>
    <SequenceOrderId>12680</SequenceOrderId>
    <Word>I have to be self compliant when I am offering someone else.</Word>
    <AlphabetSequenceIndex>512</AlphabetSequenceIndex>
    <ScriptureReference>Genesis 20:16, Psalms 34, Song of Solomon 2, 1 John 3:11</ScriptureReference>
    <ScriptureReferenceURI>http://bible.crosswalk.com/OnlineStudyBible/bible.cgi?new=1&amp;word=Genesis+20%3A16%2C+Psalms+34%2C+Song+of+Solomon+2%2C+1+John+3%3A11&amp;section=0&amp;version=nkj&amp;language=en</ScriptureReferenceURI>
  </AlphabetSequence>
  <AlphabetSequence>
    <SequenceOrderId>12681</SequenceOrderId>
    <Word>He made an offer, you followed the acception.</Word>
    <AlphabetSequenceIndex>373</AlphabetSequenceIndex>
    <ScriptureReference>Genesis 15:12, 2 Chronicles 6, Ezekiel 10, Revelation 2:12</ScriptureReference>
    <ScriptureReferenceURI>http://bible.crosswalk.com/OnlineStudyBible/bible.cgi?new=1&amp;word=Genesis+15%3A12%2C+2+Chronicles+6%2C+Ezekiel+10%2C+Revelation+2%3A12&amp;section=0&amp;version=nkj&amp;language=en</ScriptureReferenceURI>
  </AlphabetSequence>
  <AlphabetSequence>
    <SequenceOrderId>12682</SequenceOrderId>
    <Word>The least deserving is the most given.</Word>
    <AlphabetSequenceIndex>378</AlphabetSequenceIndex>
    <ScriptureReference>Genesis 15:17, 2 Chronicles 11, Ezekiel 5, Revelation 2:7</ScriptureReference>
    <ScriptureReferenceURI>http://bible.crosswalk.com/OnlineStudyBible/bible.cgi?new=1&amp;word=Genesis+15%3A17%2C+2+Chronicles+11%2C+Ezekiel+5%2C+Revelation+2%3A7&amp;section=0&amp;version=nkj&amp;language=en</ScriptureReferenceURI>
  </AlphabetSequence>
  <AlphabetSequence>
    <SequenceOrderId>12683</SequenceOrderId>
    <Word>The world knows what it has to do, it just have distance associating it.</Word>
    <AlphabetSequenceIndex>706</AlphabetSequenceIndex>
    <ScriptureReference>Genesis 26:13, Isaiah 27, Psalms 1, 1 Peter 1:22</ScriptureReference>
    <ScriptureReferenceURI>http://bible.crosswalk.com/OnlineStudyBible/bible.cgi?new=1&amp;word=Genesis+26%3A13%2C+Isaiah+27%2C+Psalms+1%2C+1+Peter+1%3A22&amp;section=0&amp;version=nkj&amp;language=en</ScriptureReferenceURI>
  </AlphabetSequence>
  <AlphabetSequence>
    <SequenceOrderId>12684</SequenceOrderId>
    <Word>For no one else.</Word>
    <AlphabetSequenceIndex>143</AlphabetSequenceIndex>
    <ScriptureReference>Genesis 6:5, Numbers 26, Acts 25, Revelation 16:5</ScriptureReference>
    <ScriptureReferenceURI>http://bible.crosswalk.com/OnlineStudyBible/bible.cgi?new=1&amp;word=Genesis+6%3A5%2C+Numbers+26%2C+Acts+25%2C+Revelation+16%3A5&amp;section=0&amp;version=nkj&amp;language=en</ScriptureReferenceURI>
  </AlphabetSequence>
  <AlphabetSequence>
    <SequenceOrderId>12685</SequenceOrderId>
    <Word>This is the beginning of the journey, we must conclude at usual time.</Word>
    <AlphabetSequenceIndex>680</AlphabetSequenceIndex>
    <ScriptureReference>Genesis 25:21, Isaiah 1, Psalms 27, 1 Peter 2:23</ScriptureReference>
    <ScriptureReferenceURI>http://bible.crosswalk.com/OnlineStudyBible/bible.cgi?new=1&amp;word=Genesis+25%3A21%2C+Isaiah+1%2C+Psalms+27%2C+1+Peter+2%3A23&amp;section=0&amp;version=nkj&amp;language=en</ScriptureReferenceURI>
  </AlphabetSequence>
  <AlphabetSequence>
    <SequenceOrderId>12686</SequenceOrderId>
    <Word>If its one instructor why numerate classes?</Word>
    <AlphabetSequenceIndex>485</AlphabetSequenceIndex>
    <ScriptureReference>Genesis 19:27, Psalms 7, Isaiah 21, 1 John 4:14</ScriptureReference>
    <ScriptureReferenceURI>http://bible.crosswalk.com/OnlineStudyBible/bible.cgi?new=1&amp;word=Genesis+19%3A27%2C+Psalms+7%2C+Isaiah+21%2C+1+John+4%3A14&amp;section=0&amp;version=nkj&amp;language=en</ScriptureReferenceURI>
  </AlphabetSequence>
  <AlphabetSequence>
    <SequenceOrderId>12687</SequenceOrderId>
    <Word>We continue to think somebody will teach us manners, but we have to observe the facts.</Word>
    <AlphabetSequenceIndex>851</AlphabetSequenceIndex>
    <ScriptureReference>Genesis 30:20, Daniel 1, 2 Kings 21, Hebrews 13:10</ScriptureReference>
    <ScriptureReferenceURI>http://bible.crosswalk.com/OnlineStudyBible/bible.cgi?new=1&amp;word=Genesis+30%3A20%2C+Daniel+1%2C+2+Kings+21%2C+Hebrews+13%3A10&amp;section=0&amp;version=nkj&amp;language=en</ScriptureReferenceURI>
  </AlphabetSequence>
  <AlphabetSequence>
    <SequenceOrderId>12688</SequenceOrderId>
    <Word>You must find the lacking to substantiate the system.</Word>
    <AlphabetSequenceIndex>577</AlphabetSequenceIndex>
    <ScriptureReference>Genesis 23:5, Psalms 99, Psalms 130, 2 Peter 3:3</ScriptureReference>
    <ScriptureReferenceURI>http://bible.crosswalk.com/OnlineStudyBible/bible.cgi?new=1&amp;word=Genesis+23%3A5%2C+Psalms+99%2C+Psalms+130%2C+2+Peter+3%3A3&amp;section=0&amp;version=nkj&amp;language=en</ScriptureReferenceURI>
  </AlphabetSequence>
  <AlphabetSequence>
    <SequenceOrderId>12689</SequenceOrderId>
    <Word>This is my son, will you refresh his after life.</Word>
    <AlphabetSequenceIndex>484</AlphabetSequenceIndex>
    <ScriptureReference>Genesis 19:26, Psalms 6, Isaiah 22, 1 John 4:15</ScriptureReference>
    <ScriptureReferenceURI>http://bible.crosswalk.com/OnlineStudyBible/bible.cgi?new=1&amp;word=Genesis+19%3A26%2C+Psalms+6%2C+Isaiah+22%2C+1+John+4%3A15&amp;section=0&amp;version=nkj&amp;language=en</ScriptureReferenceURI>
  </AlphabetSequence>
  <AlphabetSequence>
    <SequenceOrderId>12690</SequenceOrderId>
    <Word>This is what my fore fathers give to me, not what I give my forebeings.</Word>
    <AlphabetSequenceIndex>682</AlphabetSequenceIndex>
    <ScriptureReference>Genesis 25:23, Isaiah 3, Psalms 25, 1 Peter 2:21</ScriptureReference>
    <ScriptureReferenceURI>http://bible.crosswalk.com/OnlineStudyBible/bible.cgi?new=1&amp;word=Genesis+25%3A23%2C+Isaiah+3%2C+Psalms+25%2C+1+Peter+2%3A21&amp;section=0&amp;version=nkj&amp;language=en</ScriptureReferenceURI>
  </AlphabetSequence>
  <AlphabetSequence>
    <SequenceOrderId>12691</SequenceOrderId>
    <Word>She was growing up into adulthood, you into manhood.</Word>
    <AlphabetSequenceIndex>552</AlphabetSequenceIndex>
    <ScriptureReference>Genesis 22:4, Psalms 74, Proverbs 5, 1 John 1:10</ScriptureReference>
    <ScriptureReferenceURI>http://bible.crosswalk.com/OnlineStudyBible/bible.cgi?new=1&amp;word=Genesis+22%3A4%2C+Psalms+74%2C+Proverbs+5%2C+1+John+1%3A10&amp;section=0&amp;version=nkj&amp;language=en</ScriptureReferenceURI>
  </AlphabetSequence>
  <AlphabetSequence>
    <SequenceOrderId>12692</SequenceOrderId>
    <Word>We have a person in God.</Word>
    <AlphabetSequenceIndex>201</AlphabetSequenceIndex>
    <ScriptureReference>Genesis 8:17, Joshua 14, Luke 12, Revelation 12:10</ScriptureReference>
    <ScriptureReferenceURI>http://bible.crosswalk.com/OnlineStudyBible/bible.cgi?new=1&amp;word=Genesis+8%3A17%2C+Joshua+14%2C+Luke+12%2C+Revelation+12%3A10&amp;section=0&amp;version=nkj&amp;language=en</ScriptureReferenceURI>
  </AlphabetSequence>
  <AlphabetSequence>
    <SequenceOrderId>12693</SequenceOrderId>
    <Word>With much social living lack the climate.</Word>
    <AlphabetSequenceIndex>360</AlphabetSequenceIndex>
    <ScriptureReference>Genesis 14:23, 1 Chronicles 22, Ezekiel 23, Revelation 2:25</ScriptureReference>
    <ScriptureReferenceURI>http://bible.crosswalk.com/OnlineStudyBible/bible.cgi?new=1&amp;word=Genesis+14%3A23%2C+1+Chronicles+22%2C+Ezekiel+23%2C+Revelation+2%3A25&amp;section=0&amp;version=nkj&amp;language=en</ScriptureReferenceURI>
  </AlphabetSequence>
  <AlphabetSequence>
    <SequenceOrderId>12694</SequenceOrderId>
    <Word>We think you can play together, share together.</Word>
    <AlphabetSequenceIndex>470</AlphabetSequenceIndex>
    <ScriptureReference>Genesis 19:12, Job 34, Isaiah 36, 1 John 5:8</ScriptureReference>
    <ScriptureReferenceURI>http://bible.crosswalk.com/OnlineStudyBible/bible.cgi?new=1&amp;word=Genesis+19%3A12%2C+Job+34%2C+Isaiah+36%2C+1+John+5%3A8&amp;section=0&amp;version=nkj&amp;language=en</ScriptureReferenceURI>
    <Commentary>Odell Jordan odell.jordan@eimac.cpii.com Communications &amp; Power Industries 20263 Times Avenue Hayward 94541 CA USA Home: (510) 886-1600 Mobile: (510) 919-3152 Work: (650) 592-1221 Ext. 2434</Commentary>
    <ContactId>18</ContactId>
  </AlphabetSequence>
  <AlphabetSequence>
    <SequenceOrderId>12695</SequenceOrderId>
    <Word>Its a characterization control.</Word>
    <AlphabetSequenceIndex>317</AlphabetSequenceIndex>
    <ScriptureReference>Genesis 12:18, 2 Kings 4, Hosea 6, Revelation 5:6</ScriptureReference>
    <ScriptureReferenceURI>http://bible.crosswalk.com/OnlineStudyBible/bible.cgi?new=1&amp;word=Genesis+12%3A18%2C+2+Kings+4%2C+Hosea+6%2C+Revelation+5%3A6&amp;section=0&amp;version=nkj&amp;language=en</ScriptureReferenceURI>
  </AlphabetSequence>
  <AlphabetSequence>
    <SequenceOrderId>12696</SequenceOrderId>
    <Word>Its american product living in outside life.</Word>
    <AlphabetSequenceIndex>430</AlphabetSequenceIndex>
    <ScriptureReference>Genesis 18:5, Esther 4, Jeremiah 10, 3 John 1:14</ScriptureReference>
    <ScriptureReferenceURI>http://bible.crosswalk.com/OnlineStudyBible/bible.cgi?new=1&amp;word=Genesis+18%3A5%2C+Esther+4%2C+Jeremiah+10%2C+3+John+1%3A14&amp;section=0&amp;version=nkj&amp;language=en</ScriptureReferenceURI>
  </AlphabetSequence>

  <CaseBasedReasoning>
   <Dated>2004-12-11T10:35:00.0000000-08:00</Dated>
   <SequenceOrderId>2403</SequenceOrderId>
   <ContactId>769</ContactId>
   <Commentary>Dr. Martin Luther King Jr. Library http://www.sjlibrary.org 150 E. San Fernando Street San Jose 95110 CA USA (408) 808-2000.</Commentary>
  </CaseBasedReasoning>

  <CaseBasedReasoning>
   <Dated>2004-12-11T10:35:00.0000000-08:00</Dated>
   <SequenceOrderId>2404</SequenceOrderId>
   <ContactId>818</ContactId>
   <Commentary>MultiLingual Computing &amp; Technology Multilingual.com #68 Volume 15 Issue 8</Commentary>
  </CaseBasedReasoning>

  <CaseBasedReasoning>
   <Dated>2004-12-11T10:35:00.0000000-08:00</Dated>
   <SequenceOrderId>2405</SequenceOrderId>
   <ContactId>207</ContactId>
   <Commentary>WaldenPondBooks.com #1670 The Pavilion at Silicon Valley 150 South First Street San Jose 95113 CA USA (408) 294-3068</Commentary>
  </CaseBasedReasoning>

  <!--
  <Event>
   <SequenceOrderId>97</SequenceOrderId>
   <Commentary></Commentary>
  </Event>
  -->

  <!--
  <Export> 
   <SequenceOrderId>32</SequenceOrderId>
   <Commentary>
   </Commentary>
  </Export>
  -->

  <!--
  <Software>
   <SequenceOrderId>469</SequenceOrderId>
   <Commentary>
   </Commentary>
  </Software>
  -->

  <!--
  <ClassAssociates>
   <SequenceOrderId>1500</SequenceOrderId>
   <Commentary></Commentary>
  </ClassAssociates> 
  -->

  <!--
  <Contact>
   <SequenceOrderId>1203</SequenceOrderId>
   <Dated></Dated>
   <Company></Company>
   <FirstName />
   <LastName />
   <OtherName />
   <Title />
   <Suffix />
   <Commentary />
   <ScriptureReference />
   <ScriptureReferenceURI />
  </Contact>
  -->

  <!--
  <ContactEmail>
   <SequenceOrderId>82</SequenceOrderId>
   <Dated></Dated>
   <ContactId></ContactId>
   <EmailAddress></EmailAddress>
  </ContactEmail>
  -->


  <ContactURI>
   <SequenceOrderId>343</SequenceOrderId>
   <Dated>2004-12-11T10:35:00.0000000-08:00</Dated>
   <ContactId>959</ContactId>
   <InternetAddress>http://www.csuhayward.edu/aboutcsuh/president/images/rees_vitae.pdf</InternetAddress>
  </ContactURI>

  <!--
  <StreetAddress>
   <SequenceOrderId>429</SequenceOrderId>
   <Dated></Dated>
   <ContactId></ContactId>
   <AddressLine1></AddressLine1>
   <City></City>
   <State></State>
   <ZipCode></ZipCode>
   <Country></Country>
  </StreetAddress>
  -->

  <!--
  <Telephone>
   <SequenceOrderId>562</SequenceOrderId>
   <Dated></Dated>
   <ContactId></ContactId>
   <TelephoneNo></TelephoneNo>
  </Telephone>
  -->

</TheWord>

<!--
Legal filter operators are:
 =    (equal) 
 !=   (not equal) 
 &lt; less than 
 &gt; greater than
-->

<!--
HTML Special Entities
Character   Meaning        Entity   Numeric
<           Less Than      &lt;     &#60;
>           Greater Than   &gt;     &#62;
&           Ampersand      &amp;    &#38;
'           Apostrophe     &apos;   &#39;
"           Quote          &quot;   &#34;
-->